viz_manga/__init__.py
viz_manga/cli.py
viz_manga/manga_details.py
viz_manga/manga_fetch.py
viz_manga-0.1.4.dist-info/entry_points.txt
viz_manga-0.1.4.dist-info/LICENSE
viz_manga-0.1.4.dist-info/WHEEL
viz_manga-0.1.4.dist-info/METADATA
viz_manga-0.1.4.dist-info/RECORD
