Metadata-Version: 2.1
Name: viz-manga
Version: 0.1.4
Summary: Viz Manga Reader
Home-page: https://github.com/minormending/viz-manga
License: MIT
Keywords: viz,manga,reader
Author: Kevin Ramdath
Author-email: krpent@gmail.com
Requires-Python: >=3.10,<4.0
Classifier: License :: OSI Approved :: MIT License
Classifier: Programming Language :: Python :: 3
Classifier: Programming Language :: Python :: 3.10
Requires-Dist: beautifulsoup4 (>=4.11.1,<5.0.0)
Requires-Dist: requests (>=2.27.1,<3.0.0)
Requires-Dist: viz-image-deobfuscate (>=0.1.4,<0.2.0)
Project-URL: Repository, https://github.com/minormending/viz-manga
